inclua/Note.py
inclua/__init__.py
inclua/__main__.py
inclua/lua.py
inclua/luajit.py
inclua/metatype.py
inclua/namespace.py
inclua/notice.py
inclua-0.2.0.dist-info/LICENSE.txt
inclua-0.2.0.dist-info/METADATA
inclua-0.2.0.dist-info/WHEEL
inclua-0.2.0.dist-info/entry_points.txt
inclua-0.2.0.dist-info/top_level.txt
inclua-0.2.0.dist-info/RECORD
