Metadata-Version: 2.1
Name: inclua
Version: 0.2.0
Summary: C to scripting languages wrapper generator, INitialy for binding C to LUA
Home-page: https://github.com/gilzoide/inclua
Author: gilzoide
Author-email: gilzoide@gmail.com
License: GPLv3
Keywords: language bindings development
Platform: UNKNOWN
Classifier: Development Status :: 3 - Alpha
Classifier: Intended Audience :: Developers
Classifier: License :: OSI Approved :: GNU General Public License v3 or later (GPLv3+)
Classifier: Programming Language :: Python :: 2
Classifier: Programming Language :: Python :: 3
Requires-Dist: c-api-extract (>=0.4)
Requires-Dist: docopt
Requires-Dist: pyyaml
